strudelpy/__init__.py
strudelpy/tests/__init__.py
strudelpy/tests/tests.py
strudelpy-0.4.2.dist-info/LICENSE.txt
strudelpy-0.4.2.dist-info/METADATA
strudelpy-0.4.2.dist-info/WHEEL
strudelpy-0.4.2.dist-info/top_level.txt
strudelpy-0.4.2.dist-info/RECORD
