Metadata-Version: 2.1
Name: strudelpy
Version: 0.4.2
Summary: Easy as Pie Emails in Python
Home-page: https://github.com/harel/strudelpy
Download-URL: https://github.com/harel/strudelpy/archive/0.3.tar.gz
Author: Harel Malka
Author-email: harel@harelmalka.com
License: MIT
Keywords: email,smtp
Classifier: Development Status :: 4 - Beta
Classifier: License :: OSI Approved :: MIT License
Classifier: Intended Audience :: Developers
Classifier: Topic :: Communications :: Email
Classifier: Programming Language :: Python :: 2.7
Classifier: Programming Language :: Python :: 3.5
License-File: LICENSE.txt
Requires-Dist: six
